hostutil/__init__.py
hostutil-2.0.0.dist-info/METADATA
hostutil-2.0.0.dist-info/WHEEL
hostutil-2.0.0.dist-info/top_level.txt
hostutil-2.0.0.dist-info/RECORD
